[
      {
            "file": "clb.jar",
            "sum": "1e5b2e4a03c697d12ae4d773a259f9a2",
            "length": 5409976
      },
      {
            "file": "Cuu Long Bao.exe",
            "sum": "a02f2db40974bc641b5520eedb70e1fc",
            "length": 22438018
      },
      {
            "file": "fileinfo.json",
            "sum": "c88f66ee8a77f2e78be808a37a220d38",
            "length": 1124
      },
      {
            "file": "gui.exe",
            "sum": "c7dd7ab74e123dba6bfd6fc910fe63aa",
            "length": 127720
      },
      {
            "file": "gui.jar",
            "sum": "5ca06600b12dae812f9774841a521aae",
            "length": 12484742
      },
      {
            "file": "h2.exe",
            "sum": "52b27ff73d9d642014db97846031bd04",
            "length": 2836906
      },
      {
            "file": "h2.jar",
            "sum": "cdbaf954ae11dfceb658f93c181440d5",
            "length": 6549
      },
      {
            "file": "javatool-cb.dll",
            "sum": "8525bb2f92a8cd2732ec05d4b760fdbf",
            "length": 3132373
      },
      {
            "file": "resources.zip",
            "sum": "08384dde4c3cc409e97bf4ad7ca7b3d0",
            "length": 27918493
      }
]